README.txt
setup.py
pyoda/__init__.py
pyoda/auth.py
pyoda/crypto.py
pyoda/err.py
pyoda/host.py
pyoda/organization.py
pyoda/request.py
pyoda.egg-info/PKG-INFO
pyoda.egg-info/SOURCES.txt
pyoda.egg-info/dependency_links.txt
pyoda.egg-info/entry_points.txt
pyoda.egg-info/requires.txt
pyoda.egg-info/top_level.txt