Metadata-Version: 1.0
Name: pyoda
Version: 0.0.4
Summary: Python library for ODA
Home-page: https://bitbucket.org/cloudjutsu/pyoda
Author: Adria Casajus<acasajus@cloudjutsu.com>
Author-email: acasajus@cloudjutsu.com
License: MIT License
Platform: UNKNOWN
